verilog_files/bad_case.v
module bad_case (input i0 , input i1, input i2, input i3 , input [1:0] sel, output reg y);
always @(*)
begin
	case(sel)
		2'b00: y = i0;
		2'b01: y = i1;
		2'b10: y = i2;
		2'b1?: y = i3;
		//2'b11: y = i3;
	endcase
end

endmodule

verilog_files/tb_bad_case.v


`timescale 1ns / 1ps
module tb_bad_case;
	// TB_SIGNALS
	reg clk, reset   ;
	//input
	reg i0,i1,i2,i3;
	reg [1:0] sel;
	// Output
	wire y;

        // Instantiate the Unit Under Test (UUT)
	bad_case uut (
		.i0(i0),
		.i1(i1),
		.i2(i2),
		.i3(i3),
		.sel(sel),
		.y(y)
	);

	initial begin
	$dumpfile("tb_bad_case.vcd");
	$dumpvars(0,tb_bad_case);
	// Initialize Inputs
	clk = 0;
	i0 = 1'b0;
	i1 = 1'b0;
	i2 = 1'b0;
	i3 = 1'b0 ;
	reset = 1'b0; #1;
	reset = 1'b1; #10;
	reset = 1'b0; 
	
	#3000 $finish;
	end

always #200 clk = ~clk;
always #17 i0 = ~i0;
always #37 i1 = ~i1;
always #57 i2 = ~i2;
always #97 i3 = ~i3;

always @ (posedge clk , posedge reset)
begin
	if(reset)
		sel <= 2'b00;
	else
		sel <= sel + 1;
end
endmodule

verilog_files/tb_bad_case.vcd
$date
	Fri Jun  4 14:32:07 2021
$end
$version
	Icarus Verilog
$end
$timescale
	1ps
$end
$scope module tb_bad_case $end
$var wire 1 ! y $end
$var reg 1 " clk $end
$var reg 1 # i0 $end
$var reg 1 $ i1 $end
$var reg 1 % i2 $end
$var reg 1 & i3 $end
$var reg 1 ' reset $end
$var reg 2 ( sel [1:0] $end
$scope module uut $end
$var wire 1 # i0 $end
$var wire 1 $ i1 $end
$var wire 1 % i2 $end
$var wire 1 & i3 $end
$var wire 2 ) sel [1:0] $end
$var reg 1 ! y $end
$upscope $end
$upscope $end
$enddefinitions $end
#0
$dumpvars
bx )
bx (
0'
0&
0%
0$
0#
0"
x!
$end
#1000
0!
b0 (
b0 )
1'
#11000
0'
#17000
1!
1#
#34000
0!
0#
#37000
1$
#51000
1!
1#
#57000
1%
#68000
0!
0#
#74000
0$
#85000
1!
1#
#97000
1&
#102000
0!
0#
#111000
1$
#114000
0%
#119000
1!
1#
#136000
0!
0#
#148000
0$
#153000
1!
1#
#170000
0!
0#
#171000
1%
#185000
1$
#187000
1!
1#
#194000
0&
#200000
b1 (
b1 )
1"
#204000
0#
#221000
1#
#222000
0!
0$
#228000
0%
#238000
0#
#255000
1#
#259000
1!
1$
#272000
0#
#285000
1%
#289000
1#
#291000
1&
#296000
0!
0$
#306000
0#
#323000
1#
#333000
1!
1$
#340000
0#
#342000
0%
#357000
1#
#370000
0!
0$
#374000
0#
#388000
0&
#391000
1#
#399000
1%
#400000
0"
#407000
1!
1$
#408000
0#
#425000
1#
#442000
0#
#444000
0!
0$
#456000
0%
#459000
1#
#476000
0#
#481000
1!
1$
#485000
1&
#493000
1#
#510000
0#
#513000
1%
#518000
0!
0$
#527000
1#
#544000
0#
#555000
1!
1$
#561000
1#
#570000
0%
#578000
0#
#582000
0&
#592000
0!
0$
#595000
1#
#600000
b10 (
b10 )
1"
#612000
0#
#627000
1!
1%
#629000
1#
1$
#646000
0#
#663000
1#
#666000
0$
#679000
1&
#680000
0#
#684000
0!
0%
#697000
1#
#703000
1$
#714000
0#
#731000
1#
#740000
0$
#741000
1!
1%
#748000
0#
#765000
1#
#776000
0&
#777000
1$
#782000
0#
#798000
0!
0%
#799000
1#
#800000
0"
#814000
0$
#816000
0#
#833000
1#
#850000
0#
#851000
1$
#855000
1!
1%
#867000
1#
#873000
1&
#884000
0#
#888000
0$
#901000
1#
#912000
0!
0%
#918000
0#
#925000
1$
#935000
1#
#952000
0#
#962000
0$
#969000
1!
1#
1%
#970000
0&
#986000
0#
#999000
1$
#1000000
b11 (
b11 )
1"
#1003000
1#
#1020000
0#
#1026000
0%
#1036000
0$
#1037000
1#
#1054000
0#
#1067000
1&
#1071000
1#
#1073000
1$
#1083000
1%
#1088000
0#
#1105000
1#
#1110000
0$
#1122000
0#
#1139000
1#
#1140000
0%
#1147000
1$
#1156000
0#
#1164000
0&
#1173000
1#
#1184000
0$
#1190000
0#
#1197000
1%
#1200000
0"
#1207000
1#
#1221000
1$
#1224000
0#
#1241000
1#
#1254000
0%
#1258000
0#
0$
#1261000
1&
#1275000
1#
#1292000
0#
#1295000
1$
#1309000
1#
#1311000
1%
#1326000
0#
#1332000
0$
#1343000
1#
#1358000
0&
#1360000
0#
#1368000
0%
#1369000
1$
#1377000
1#
#1394000
0#
#1400000
0!
b0 (
b0 )
1"
#1406000
0$
#1411000
1!
1#
#1425000
1%
#1428000
0!
0#
#1443000
1$
#1445000
1!
1#
#1455000
1&
#1462000
0!
0#
#1479000
1!
1#
#1480000
0$
#1482000
0%
#1496000
0!
0#
#1513000
1!
1#
#1517000
1$
#1530000
0!
0#
#1539000
1%
#1547000
1!
1#
#1552000
0&
#1554000
0$
#1564000
0!
0#
#1581000
1!
1#
#1591000
1$
#1596000
0%
#1598000
0!
0#
#1600000
0"
#1615000
1!
1#
#1628000
0$
#1632000
0!
0#
#1649000
1!
1#
1&
#1653000
1%
#1665000
1$
#1666000
0!
0#
#1683000
1!
1#
#1700000
0!
0#
#1702000
0$
#1710000
0%
#1717000
1!
1#
#1734000
0!
0#
#1739000
1$
#1746000
0&
#1751000
1!
1#
#1767000
1%
#1768000
0!
0#
#1776000
0$
#1785000
1!
1#
#1800000
0!
b1 (
b1 )
1"
#1802000
0#
#1813000
1!
1$
#1819000
1#
#1824000
0%
#1836000
0#
#1843000
1&
#1850000
0!
0$
#1853000
1#
#1870000
0#
#1881000
1%
#1887000
1!
1#
1$
#1904000
0#
#1921000
1#
#1924000
0!
0$
#1938000
0#
0%
#1940000
0&
#1955000
1#
#1961000
1!
1$
#1972000
0#
#1989000
1#
#1995000
1%
#1998000
0!
0$
#2000000
0"
#2006000
0#
#2023000
1#
#2035000
1!
1$
#2037000
1&
#2040000
0#
#2052000
0%
#2057000
1#
#2072000
0!
0$
#2074000
0#
#2091000
1#
#2108000
0#
#2109000
1!
1$
1%
#2125000
1#
#2134000
0&
#2142000
0#
#2146000
0!
0$
#2159000
1#
#2166000
0%
#2176000
0#
#2183000
1!
1$
#2193000
1#
#2200000
0!
b10 (
b10 )
1"
#2210000
0#
#2220000
0$
#2223000
1!
1%
#2227000
1#
#2231000
1&
#2244000
0#
#2257000
1$
#2261000
1#
#2278000
0#
#2280000
0!
0%
#2294000
0$
#2295000
1#
#2312000
0#
#2328000
0&
#2329000
1#
#2331000
1$
#2337000
1!
1%
#2346000
0#
#2363000
1#
#2368000
0$
#2380000
0#
#2394000
0!
0%
#2397000
1#
#2400000
0"
#2405000
1$
#2414000
0#
#2425000
1&
#2431000
1#
#2442000
0$
#2448000
0#
#2451000
1!
1%
#2465000
1#
#2479000
1$
#2482000
0#
#2499000
1#
#2508000
0!
0%
#2516000
0#
0$
#2522000
0&
#2533000
1#
#2550000
0#
#2553000
1$
#2565000
1!
1%
#2567000
1#
#2584000
0#
#2590000
0$
#2600000
b11 (
b11 )
1"
#2601000
1#
#2618000
0#
#2619000
1&
#2622000
0%
#2627000
1$
#2635000
1#
#2652000
0#
#2664000
0$
#2669000
1#
#2679000
1%
#2686000
0#
#2701000
1$
#2703000
1#
#2716000
0&
#2720000
0#
#2736000
0%
#2737000
1#
#2738000
0$
#2754000
0#
#2771000
1#
#2775000
1$
#2788000
0#
#2793000
1%
#2800000
0"
#2805000
1#
#2812000
0$
#2813000
1&
#2822000
0#
#2839000
1#
#2849000
1$
#2850000
0%
#2856000
0#
#2873000
1#
#2886000
0$
#2890000
0#
#2907000
1#
1%
#2910000
0&
#2923000
1$
#2924000
0#
#2941000
1#
#2958000
0#
#2960000
0$
#2964000
0%
#2975000
1#
#2992000
0#
#2997000
1$
#3000000
0!
b0 (
b0 )
1"
#3007000
1&
#3009000
1!
1#
